jasmine_runner
tests
