Metadata-Version: 1.0
Name: jasmine-splinter-runner
Version: 0.6.1
Summary: jasmine runner based on splinter
Home-page: UNKNOWN
Author: CobraTeam
Author-email: francisco@franciscosouza.net
License: UNKNOWN
Platform: UNKNOWN
